setup.cfg
setup.py
natty/__init__.py
natty.egg-info/PKG-INFO
natty.egg-info/SOURCES.txt
natty.egg-info/dependency_links.txt
natty.egg-info/not-zip-safe
natty.egg-info/requires.txt
natty.egg-info/top_level.txt
natty/data/natty-basic-parser-0.2.0.jar