Metadata-Version: 1.1
Name: natty
Version: 0.2.4
Summary: Python interface to Natty Date Parser
Home-page: https://github.com/eadmundo/python-natty
Author: Edward Stone
Author-email: edwardjstone@yahoo.com
License: MIT
Download-URL: https://github.com/eadmundo/python-natty/archive/v0.2.4.tar.gz
Keywords: natty
Platform: UNKNOWN
Classifier: Development Status :: 3 - Alpha
Classifier: Environment :: Console
Classifier: Intended Audience :: Developers
Classifier: License :: OSI Approved :: Apache Software License
Classifier: Operating System :: OS Independent
Classifier: Programming Language :: Python :: 2.7
Classifier: Natural Language :: English
